mfd_traffic_manager/__init__.py
mfd_traffic_manager/base.py
mfd_traffic_manager/exceptions.py
mfd_traffic_manager/manager.py
mfd_traffic_manager/single_host_stream.py
mfd_traffic_manager/stream.py
mfd_traffic_manager/stress_traffic_manager.py
mfd_traffic_manager/utils/__init__.py
mfd_traffic_manager/utils/ip.py
mfd_traffic_manager-1.18.0.dist-info/licenses/AUTHORS.md
mfd_traffic_manager-1.18.0.dist-info/licenses/LICENSE.md
mfd_traffic_manager-1.18.0.dist-info/METADATA
mfd_traffic_manager-1.18.0.dist-info/WHEEL
mfd_traffic_manager-1.18.0.dist-info/top_level.txt
mfd_traffic_manager-1.18.0.dist-info/RECORD
