Metadata-Version: 2.4
Name: mfd-traffic-manager
Version: 1.18.0
Summary: Module for handling variety types of traffic under one consistent API.
Project-URL: Homepage, https://github.com/intel/mfd
Project-URL: Repository, https://github.com/intel/mfd-traffic-manager
Project-URL: Issues, https://github.com/intel/mfd-traffic-manager/issues
Project-URL: Changelog, https://github.com/intel/mfd-traffic-manager/blob/main/CHANGELOG.md
Requires-Python: <3.14,>=3.10
License-File: LICENSE.md
License-File: AUTHORS.md
Requires-Dist: mfd-common-libs>=1.11.0
Dynamic: license-file
